desktop/__init__.py
desktop/client.py
desktop_by_harmless-0.1.0.dist-info/METADATA
desktop_by_harmless-0.1.0.dist-info/WHEEL
desktop_by_harmless-0.1.0.dist-info/top_level.txt
desktop_by_harmless-0.1.0.dist-info/RECORD
