Metadata-Version: 2.1
Name: desktop_by_harmless
Version: 0.1.0
Summary: Un package Python pour importer les fichiers de votre ordinateur 
Home-page: https://github.com/MaxLinkerluabug/desktop
Author: Moi
Author-email: tunelaurapas@gmail.com
Classifier: Programming Language :: Python :: 3
Classifier: License :: OSI Approved :: MIT License
Classifier: Operating System :: OS Independent
Requires-Python: >=3.6
Requires-Dist: numpy
Requires-Dist: requests
